ecss_allure_report/__init__.py
ecss_allure_report/diagram.py
ecss_allure_report/summary.py
ecss_allure_report-1.3.0.dist-info/licenses/LICENSE
ecss_allure_report-1.3.0.dist-info/METADATA
ecss_allure_report-1.3.0.dist-info/WHEEL
ecss_allure_report-1.3.0.dist-info/top_level.txt
ecss_allure_report-1.3.0.dist-info/RECORD
